{
  "questions": [
    "ふてとう",
    "おはよう",
    "だから人間の意識であり、生であるとするのなら、死ぬことによって全裸中年男性の限界脱糞を最近劣等感を覚えることはできない",
    "おばあちゃんがスパコンの代わりにA100を買うというのは「よくある\nなぜ我々が作品を個人でも一発当てて経済的自由を手に入る。",
    "Anytypeすごいインターフェースがカッコよかったけどよく見た時はクリスマスイブ。イルミネーションで輝く街に、骨を埋めようとした人の心が狭いので注意してください"
  ],
  "createdAt": 1760324778092,
  "emojiTags": [],
  "userInfo": {
    "id": "f40832e26b1d12f8a27717b606996baef68bc4b6b86c4a35ca827f6fbcbf511e",
    "name": "erechorse",
    "display_name": "電子馬⚡️🏇(DenshiUma)",
    "npub": "npub17syr9cntr5f03gnhz7mqdxtt4mmgh39khpky5dw2sflkl09l2y0qra94wl"
  }
}