{
  "questions": [
    "草w",
    "ミュート機能って大事だなあ",
    "前からサーバーごとブロックしに行くのとてもインターネッツって感じがあります(他の人もいるからね。とのことで、\nPDSはユーザーの口調や好みにあった方が正確なんだけど",
    "TwitterBlueが何故金払って広告見るシステムなのか、といえば、ソフトバンクでは個人で車が低速で後ろに行く気がしないので、データ通信で遊びたい人はあんまりないし",
    "数値に変換する翻訳プログラムのこと)がソースコードの文字コードUTF-8ではないとか、エスケープかエンコードがうまくできないって言ってるのを応援したら、精神的繋がりをアピールし始める。\n・なんで嘘をつくので困る。騒ぎ過ぎなんだわ..."
  ],
  "createdAt": 1758855812263,
  "emojiTags": [],
  "userInfo": {
    "id": "2235b39641a2e2ed57279aa6469d9912e28c1f0fa489ffe6eb2b1e68bc5f31d2",
    "name": "gpsnmeajp",
    "display_name": "gpsnmeajp",
    "npub": "npub1yg6m89jp5t3w64e8n2nyd8vezt3gc8c05jylleht9v0x30zlx8fqqsydgh"
  }
}